astrolab/__init__.py
astrolab-0.1.0.dist-info/METADATA
astrolab-0.1.0.dist-info/WHEEL
astrolab-0.1.0.dist-info/entry_points.txt
astrolab-0.1.0.dist-info/top_level.txt
astrolab-0.1.0.dist-info/RECORD
